{
  "Name": "Demon Horns Small",
  "FrontHat": {
    "StartingPosition": {
      "X": 0,
      "Y": 0
    },
    "HeadPosition": {
      "X": -6,
      "Y": -4
    },
    "HatSize": {
      "Width": 8,
      "Length": 4
    }
  },
  "RightHat": {
    "StartingPosition": {
      "X": 0,
      "Y": 5
    },
    "HeadPosition": {
      "X": -5,
      "Y": -4
    },
    "HatSize": {
      "Width": 8,
      "Length": 4
    }
  },
  "LeftHat": {
    "StartingPosition": {
      "X": 0,
      "Y": 10
    },
    "HeadPosition": {
      "X": -7,
      "Y": -4
    },
    "HatSize": {
      "Width": 8,
      "Length": 4
    }
  },
  "BackHat": {
  "DrawOrderOverride": {
      "Preposition": "Before",
      "AppearanceType": "Hair"
	  },
    "StartingPosition": {
      "X": 0,
      "Y": 15
    },
    "HeadPosition": {
      "X": -6,
      "Y": -5
    },
    "HatSize": {
      "Width": 8,
      "Length": 4
    }
  }
}