{
	"Changes": [
		{
			"LogName": "Daffodil Festival Shop",
			"Action": "EditData",
			"Target": "Data/Shops",
			"TargetField": [
				"Festival_NightMarket_MagicBoat_Day1",
				"Items"
			],
			"Entries": {
				"ZoeyHoshi.ForageCrops_DaffodilSeeds": {
					"Id": "ZoeyHoshi.ForageCrops_DaffodilSeeds",
					"ItemId": "(O)ZoeyHoshi.ForageCrops_DaffodilSeeds"
				}
			},
			"MoveEntries": [
				{
					"Id": "ZoeyHoshi.ForageCrops_DaffodilSeeds",
					"AfterId": "(O)429"
				}
			],
			"When": {
				"DaffodilCrop": true
			}

		},
		{
			"LogName": "Dandelion Festival Shop",
			"Action": "EditData",
			"Target": "Data/Shops",
			"TargetField": [
				"Festival_NightMarket_MagicBoat_Day1",
				"Items"
			],
			"Entries": {
				"ZoeyHoshi.ForageCrops_DandelionSeeds": {
					"Id": "ZoeyHoshi.ForageCrops_DandelionSeeds",
					"ItemId": "(O)ZoeyHoshi.ForageCrops_DandelionSeeds"
				}
			},
			"MoveEntries": [
				{
					"Id": "ZoeyHoshi.ForageCrops_DandelionSeeds",
					"AfterId": "(O)429"
				}
			],
			"When": {
				"DandelionCrop": true
			}
		},
		{
			"LogName": "Leek Festival Shop",
			"Action": "EditData",
			"Target": "Data/Shops",
			"TargetField": [
				"Festival_NightMarket_MagicBoat_Day1",
				"Items"
			],
			"Entries": {
				"ZoeyHoshi.ForageCrops_LeekSeeds": {
					"Id": "ZoeyHoshi.ForageCrops_LeekSeeds",
					"ItemId": "(O)ZoeyHoshi.ForageCrops_LeekSeeds"
				}
			},
			"MoveEntries": [
				{
					"Id": "ZoeyHoshi.ForageCrops_LeekSeeds",
					"AfterId": "(O)429"
				}
			],
			"When": {
				"LeekCrop": true
			}
		},
		{
			"LogName": "Wild Horseradish Festival Shop",
			"Action": "EditData",
			"Target": "Data/Shops",
			"TargetField": [
				"Festival_NightMarket_MagicBoat_Day1",
				"Items"
			],
			"Entries": {
				"ZoeyHoshi.ForageCrops_WildHorseradishSeeds": {
					"Id": "ZoeyHoshi.ForageCrops_WildHorseradishSeeds",
					"ItemId": "(O)ZoeyHoshi.ForageCrops_WildHorseradishSeeds"
				}
			},
			"MoveEntries": [
				{
					"Id": "ZoeyHoshi.ForageCrops_WildHorseradishSeeds",
					"AfterId": "(O)429"
				}
			],
			"When": {
				"WildHorseradishCrop": true
			}
		},
		{
			"LogName": "Fiddlehead Fern Festival Shop",
			"Action": "EditData",
			"Target": "Data/Shops",
			"TargetField": [
				"Festival_NightMarket_MagicBoat_Day2",
				"Items"
			],
			"Entries": {
				"ZoeyHoshi.ForageCrops_FiddleheadFernSeeds": {
					"Id": "ZoeyHoshi.ForageCrops_FiddleheadFernSeeds",
					"ItemId": "(O)ZoeyHoshi.ForageCrops_FiddleheadFernSeeds"
				}
			},
			"MoveEntries": [
				{
					"Id": "ZoeyHoshi.ForageCrops_FiddleheadFernSeeds",
					"AfterId": "(O)431"
				}
			],
			"When": {
				"FiddleheadFernCrop": true
			}
		}
	]
}